README
setup.py
src/python_ssmi.egg-info/PKG-INFO
src/python_ssmi.egg-info/SOURCES.txt
src/python_ssmi.egg-info/dependency_links.txt
src/python_ssmi.egg-info/requires.txt
src/python_ssmi.egg-info/top_level.txt
src/ssmi/__init__.py
src/ssmi/client.py
src/ssmi/errors.py
src/ssmi/tests/__init__.py
src/ssmi/tests/test_client.py
src/ssmi/tests/test_errors.py