Metadata-Version: 1.0
Name: python-ssmi
Version: 0.0.6
Summary: Python module implementing SSMI for USSD and SMS.
Home-page: http://github.com/praekelt/python-ssmi
Author: Praekelt Foundation
Author-email: dev@praekeltfoundation.org
License: BSD
Platform: UNKNOWN
Classifier: Development Status :: 4 - Beta
Classifier: Intended Audience :: Developers
Classifier: License :: OSI Approved :: BSD License
Classifier: Operating System :: POSIX
Classifier: Programming Language :: Python
Classifier: Topic :: Software Development :: Libraries :: Python Modules
Classifier: Topic :: System :: Networking
